ignoreme/__init__.py
ignoreme/api_client.py
ignoreme/main.py
ignoreme-1.0.3.dist-info/licenses/LICENSE
ignoreme-1.0.3.dist-info/METADATA
ignoreme-1.0.3.dist-info/WHEEL
ignoreme-1.0.3.dist-info/entry_points.txt
ignoreme-1.0.3.dist-info/top_level.txt
ignoreme-1.0.3.dist-info/RECORD
