Metadata-Version: 2.4
Name: ignoreme
Version: 1.0.3
Summary: A Python client for donotcommit.com
Author-email: Dêvid Teófilo <nnick4673@gmail.com>
License-Expression: MIT
Project-URL: Homepage, https://github.com/devid8642/ignoreme
Project-URL: Issues, https://github.com/devid8642/ignoreme/issues
Requires-Python: >=3.12
License-File: LICENSE
Requires-Dist: httpx>=0.28.1
Requires-Dist: typer>=0.15.2
Dynamic: license-file
